{
  "projectName": "Metr0 Madne55",
  "artistName": "",
  "projectBPM": 162,
  "currentSequence": 0,
  "channelURLs": [
    "/content/e7d344ef3098d0889856978c4d2e81ccf2358f7f8b66feecc71e03036c59ad48i0",
    "/content/d030eb3d8bcd68b0ed02b0c67fdb981342eea40b0383814f179a48e76927db93i0",
    "/content/ef5707e6ecf4d5b6edb4c3a371ca1c57b5d1057c6505ccb5f8bdc8918b0c4d94i0",
    "/content/d030eb3d8bcd68b0ed02b0c67fdb981342eea40b0383814f179a48e76927db93i0",
    "/content/5a42d7b2e2fe01e4f31cbad5dd671997f87339d970faaab37f6355c4a2f3be5ai0",
    "/content/0b69fb6734a3e267093e5b9d9c5af70a847c021922c168a9d573659ea63fa7adi0",
    "/content/91f52a4ca00bb27383ae149f24b605d75ea99df033a6cbb6de2389455233bf51i0",
    "/content/ddc1838c1a6a3c45b2c6e19ff278c3b51b0797c3f1339c533370442d23687a68i0",
    "/content/1e3c2571e96729153e4b63e2b561d85aec7bc5ba372d293af469a525dfa3ed59i0",
    "/content/437868aecce108d49f9b29c2f477987cb5834ffdf639a650335af7f0fdd5e55bi0",
    "/content/9bd9a19c8a067dda7bd63cf57c67bec68b16ec3c5258d53ec5d9b47391c89219i0",
    "/content/bd02c39ac1adad2c4a5f79dd4a6a9f08549488348cdf7e669a397840eb2673e1i0",
    "/content/e070d07283f4a41a8a60fda4462814046ac5d342a4afac407e8b1f57f334fb52i0",
    "/content/f4161e0da85db42f30000e80f7923b4c59bcefd368c4c93a391efbac2c094b30i0",
    "/content/c511a6247dd207f6ebbf87090193d661f440a7f198c0009e49ed4c1b3541914fi0",
    "/content/bd02c39ac1adad2c4a5f79dd4a6a9f08549488348cdf7e669a397840eb2673e1i0"
  ],
  "channelVolume": [
    1,
    0.57,
    1.67,
    0.23,
    0.24,
    0.49,
    1,
    1,
    1,
    0.42,
    1.34,
    1,
    1,
    1,
    1,
    1
  ],
  "channelPlaybackSpeed": [
    1,
    1,
    1,
    1,
    1.12,
    1,
    1,
    1,
    1,
    1,
    0.16,
    1,
    1,
    1,
    1,
    1
  ],
  "trimSettings": [
    {
      "startSliderValue": 0.01,
      "endSliderValue": 100,
      "totalSampleDuration": 1.1156458333333332
    },
    {
      "startSliderValue": 0.01,
      "endSliderValue": 100,
      "totalSampleDuration": 0.06552083333333333
    },
    {
      "startSliderValue": 0.01,
      "endSliderValue": 100,
      "totalSampleDuration": 0.30814583333333334
    },
    {
      "startSliderValue": 0.01,
      "endSliderValue": 100,
      "totalSampleDuration": 0.241125
    },
    {
      "startSliderValue": 0.01,
      "endSliderValue": 100,
      "totalSampleDuration": 2.037541666666667
    },
    {
      "startSliderValue": 0.01,
      "endSliderValue": 3.609168970650787,
      "totalSampleDuration": 0.0008541666666666667,
      "start": 0.01,
      "end": 3.609168970650787
    },
    {
      "startSliderValue": 0.01,
      "endSliderValue": 59.26031528791565,
      "totalSampleDuration": 0.173875
    },
    {
      "startSliderValue": 0.01,
      "endSliderValue": 100,
      "totalSampleDuration": 0.161875
    },
    {
      "startSliderValue": 0.01,
      "endSliderValue": 100,
      "totalSampleDuration": 0.3333333333333333
    },
    {
      "startSliderValue": 0.01,
      "endSliderValue": 100,
      "totalSampleDuration": 0.4615625
    },
    {
      "startSliderValue": 59.17528445342407,
      "endSliderValue": 71.45081215440237,
      "totalSampleDuration": 0.30814583333333334,
      "start": 59.17528445342407,
      "end": 71.45081215440237
    },
    {
      "startSliderValue": 6.659316707218167,
      "endSliderValue": 81.10992929050815,
      "totalSampleDuration": 0.7422291666666667,
      "start": 6.659316707218167,
      "end": 81.10992929050815
    },
    {
      "startSliderValue": 5.281199310624493,
      "endSliderValue": 52.39253852392538,
      "totalSampleDuration": 0.6206041666666666,
      "start": 5.281199310624493,
      "end": 52.39253852392538
    },
    {
      "startSliderValue": 3.578036293592863,
      "endSliderValue": 33.09002433090024,
      "totalSampleDuration": 1.065875
    },
    {
      "startSliderValue": 4.4701693025141935,
      "endSliderValue": 68.28872668288727,
      "totalSampleDuration": 0.780125
    },
    {
      "startSliderValue": 6.578847323600972,
      "endSliderValue": 15.514750608272507,
      "totalSampleDuration": 0.7422291666666667
    }
  ],
  "projectChannelNames": [
    "VB 808 Kick",
    "808 Closed Hat",
    "808 Snare",
    "Quiet Hat",
    "Crash",
    "Load Sample",
    "Synth Bass",
    "Synth Bass",
    "Load Sample",
    "Hard Kick",
    "Spesh FX",
    "BASED",
    "OH",
    "BE",
    "ONE",
    "B"
  ],
  "projectSequences": {
    "Sequence0": {
      "ch0": {
        "steps": [
          1,
          7,
          13,
          19,
          25,
          29,
          33,
          39,
          45,
          51,
          57,
          59,
          61,
          63
        ]
      },
      "ch1": {
        "steps": [
          1,
          3,
          5,
          7,
          9,
          11,
          13,
          15,
          17,
          19,
          21,
          23,
          25,
          27,
          29,
          31,
          33,
          35,
          37,
          39,
          41,
          43,
          45,
          47,
          49,
          51,
          53,
          55,
          57,
          59,
          61,
          63
        ]
      },
      "ch2": {
        "steps": []
      },
      "ch3": {
        "steps": []
      },
      "ch4": {
        "steps": [
          1,
          7,
          13,
          19,
          25,
          29,
          33,
          39,
          45,
          51,
          57,
          59,
          61,
          63
        ]
      },
      "ch5": {
        "steps": []
      },
      "ch6": {
        "steps": [
          1,
          7,
          13,
          19,
          25,
          29,
          33,
          39,
          45,
          51,
          57,
          59,
          61,
          63
        ]
      },
      "ch7": {
        "steps": [
          3,
          9,
          15,
          21,
          35,
          41,
          47,
          53
        ]
      },
      "ch8": {
        "steps": [
          5,
          11,
          17,
          23,
          27,
          31,
          37,
          43,
          49,
          55,
          57,
          59,
          61,
          63
        ]
      },
      "ch9": {
        "steps": []
      },
      "ch10": {
        "steps": []
      },
      "ch11": {
        "steps": []
      },
      "ch12": {
        "steps": []
      },
      "ch13": {
        "steps": []
      },
      "ch14": {
        "steps": []
      },
      "ch15": {
        "steps": []
      }
    },
    "Sequence1": {
      "ch0": {
        "steps": [
          1,
          15,
          19,
          21,
          27,
          31,
          33,
          47,
          51,
          53,
          59
        ]
      },
      "ch1": {
        "steps": [
          1,
          3,
          5,
          7,
          9,
          11,
          13,
          15,
          17,
          19,
          21,
          23,
          25,
          27,
          29,
          31,
          33,
          35,
          37,
          39,
          41,
          43,
          45,
          47,
          49,
          51,
          53,
          55,
          57,
          58,
          59,
          60,
          61,
          62,
          63,
          64
        ]
      },
      "ch2": {
        "steps": [
          9,
          25,
          41,
          57,
          63
        ]
      },
      "ch3": {
        "steps": []
      },
      "ch4": {
        "steps": [
          1
        ]
      },
      "ch5": {
        "steps": [
          37
        ]
      },
      "ch6": {
        "steps": [
          1,
          5,
          29,
          33,
          35
        ]
      },
      "ch7": {
        "steps": [
          3,
          31
        ]
      },
      "ch8": {
        "steps": [
          5,
          33,
          35
        ]
      },
      "ch9": {
        "steps": []
      },
      "ch10": {
        "steps": [
          1
        ]
      },
      "ch11": {
        "steps": []
      },
      "ch12": {
        "steps": []
      },
      "ch13": {
        "steps": []
      },
      "ch14": {
        "steps": []
      },
      "ch15": {
        "steps": [
          1,
          3,
          15,
          19,
          21,
          29,
          33,
          35,
          47,
          51,
          53,
          55
        ]
      }
    },
    "Sequence2": {
      "ch0": {
        "steps": [
          1,
          15,
          19,
          21,
          27,
          31,
          33,
          47,
          51,
          53
        ]
      },
      "ch1": {
        "steps": [
          1,
          3,
          5,
          7,
          9,
          10,
          11,
          13,
          15,
          17,
          19,
          21,
          23,
          25,
          27,
          29,
          31,
          33,
          35,
          37,
          39,
          41,
          43,
          45,
          47,
          49,
          51,
          53,
          55,
          57,
          59
        ]
      },
      "ch2": {
        "steps": [
          9,
          25,
          41,
          57
        ]
      },
      "ch3": {
        "steps": []
      },
      "ch4": {
        "steps": [
          1
        ]
      },
      "ch5": {
        "steps": []
      },
      "ch6": {
        "steps": [
          1,
          5,
          29,
          33,
          35
        ]
      },
      "ch7": {
        "steps": [
          3,
          31
        ]
      },
      "ch8": {
        "steps": [
          5,
          33,
          35
        ]
      },
      "ch9": {
        "steps": []
      },
      "ch10": {
        "steps": [
          {
            "index": 1,
            "reverse": true
          }
        ]
      },
      "ch11": {
        "steps": []
      },
      "ch12": {
        "steps": []
      },
      "ch13": {
        "steps": []
      },
      "ch14": {
        "steps": []
      },
      "ch15": {
        "steps": [
          1,
          3,
          15,
          19,
          21,
          29,
          33,
          35,
          47,
          51,
          53,
          54,
          55
        ]
      }
    },
    "Sequence3": {
      "ch0": {
        "steps": [
          1,
          15,
          19,
          21,
          27,
          31,
          33,
          47,
          51,
          53,
          59
        ]
      },
      "ch1": {
        "steps": [
          1,
          3,
          5,
          7,
          9,
          11,
          13,
          15,
          17,
          19,
          21,
          23,
          25,
          27,
          29,
          31,
          33,
          35,
          37,
          39,
          41,
          43,
          45,
          47,
          49,
          51,
          53,
          55,
          57,
          58,
          59,
          60,
          61,
          62,
          63,
          64
        ]
      },
      "ch2": {
        "steps": [
          9,
          25,
          41,
          57,
          63
        ]
      },
      "ch3": {
        "steps": []
      },
      "ch4": {
        "steps": [
          1
        ]
      },
      "ch5": {
        "steps": [
          17
        ]
      },
      "ch6": {
        "steps": [
          1,
          9,
          29,
          33,
          35
        ]
      },
      "ch7": {
        "steps": [
          3,
          7,
          31
        ]
      },
      "ch8": {
        "steps": [
          5,
          33,
          35
        ]
      },
      "ch9": {
        "steps": []
      },
      "ch10": {
        "steps": [
          1
        ]
      },
      "ch11": {
        "steps": []
      },
      "ch12": {
        "steps": []
      },
      "ch13": {
        "steps": [
          15,
          19,
          33,
          35,
          49
        ]
      },
      "ch14": {
        "steps": []
      },
      "ch15": {
        "steps": [
          1,
          3,
          15,
          19,
          21,
          29,
          33,
          35,
          47,
          51,
          53
        ]
      }
    },
    "Sequence4": {
      "ch0": {
        "steps": [
          1,
          15,
          19,
          21,
          27,
          31,
          33,
          47,
          51,
          53
        ]
      },
      "ch1": {
        "steps": [
          1,
          3,
          5,
          7,
          9,
          10,
          11,
          13,
          15,
          17,
          19,
          21,
          23,
          25,
          27,
          29,
          31,
          33,
          35,
          37,
          39,
          41,
          43,
          45
        ]
      },
      "ch2": {
        "steps": [
          9,
          25,
          41,
          57
        ]
      },
      "ch3": {
        "steps": [
          47,
          49,
          51,
          53,
          55,
          57,
          59
        ]
      },
      "ch4": {
        "steps": [
          1
        ]
      },
      "ch5": {
        "steps": []
      },
      "ch6": {
        "steps": [
          1,
          9,
          29,
          33
        ]
      },
      "ch7": {
        "steps": [
          3,
          7,
          31
        ]
      },
      "ch8": {
        "steps": [
          5,
          33
        ]
      },
      "ch9": {
        "steps": []
      },
      "ch10": {
        "steps": [
          {
            "index": 1,
            "reverse": true
          }
        ]
      },
      "ch11": {
        "steps": []
      },
      "ch12": {
        "steps": []
      },
      "ch13": {
        "steps": [
          15,
          19,
          33,
          57
        ]
      },
      "ch14": {
        "steps": []
      },
      "ch15": {
        "steps": [
          1,
          3,
          15,
          19,
          21,
          29,
          33,
          35
        ]
      }
    },
    "Sequence5": {
      "ch0": {
        "steps": [
          1,
          15,
          19,
          21,
          27,
          31,
          33,
          47,
          51,
          53,
          59
        ]
      },
      "ch1": {
        "steps": [
          1,
          3,
          5,
          7,
          9,
          11,
          13,
          15,
          17,
          19,
          21,
          23,
          25,
          27,
          29,
          31,
          33,
          35,
          37,
          39,
          41,
          43,
          45,
          47,
          49,
          51,
          53,
          55,
          57,
          58,
          59,
          60,
          61,
          62,
          63,
          64
        ]
      },
      "ch2": {
        "steps": [
          9,
          25,
          41,
          57,
          63
        ]
      },
      "ch3": {
        "steps": []
      },
      "ch4": {
        "steps": [
          1
        ]
      },
      "ch5": {
        "steps": [
          37
        ]
      },
      "ch6": {
        "steps": [
          1,
          9,
          21,
          29
        ]
      },
      "ch7": {
        "steps": [
          3,
          7,
          23,
          27
        ]
      },
      "ch8": {
        "steps": [
          5,
          25
        ]
      },
      "ch9": {
        "steps": []
      },
      "ch10": {
        "steps": [
          1
        ]
      },
      "ch11": {
        "steps": []
      },
      "ch12": {
        "steps": [
          29,
          30,
          31,
          33
        ]
      },
      "ch13": {
        "steps": [
          15,
          19,
          49
        ]
      },
      "ch14": {
        "steps": []
      },
      "ch15": {
        "steps": [
          1,
          3,
          15,
          19,
          21,
          35,
          47,
          51,
          53
        ]
      }
    },
    "Sequence6": {
      "ch0": {
        "steps": [
          1,
          15,
          19,
          21,
          27,
          31,
          33,
          47,
          51,
          53
        ]
      },
      "ch1": {
        "steps": [
          1,
          3,
          5,
          7,
          9,
          10,
          11,
          13,
          15,
          17,
          19,
          21,
          23,
          25,
          27,
          41,
          43,
          45,
          47,
          49,
          51,
          53,
          55
        ]
      },
      "ch2": {
        "steps": [
          9,
          25,
          41,
          57,
          63
        ]
      },
      "ch3": {
        "steps": [
          29,
          31,
          33,
          35,
          37,
          39,
          57,
          59,
          61
        ]
      },
      "ch4": {
        "steps": [
          1
        ]
      },
      "ch5": {
        "steps": []
      },
      "ch6": {
        "steps": [
          1,
          9,
          21
        ]
      },
      "ch7": {
        "steps": [
          3,
          7,
          23,
          27
        ]
      },
      "ch8": {
        "steps": [
          5,
          25
        ]
      },
      "ch9": {
        "steps": []
      },
      "ch10": {
        "steps": [
          {
            "index": 1,
            "reverse": true
          }
        ]
      },
      "ch11": {
        "steps": []
      },
      "ch12": {
        "steps": [
          29,
          30,
          31,
          33,
          35,
          37,
          38,
          39,
          57,
          59,
          61,
          62,
          63
        ]
      },
      "ch13": {
        "steps": [
          15,
          19,
          49
        ]
      },
      "ch14": {
        "steps": []
      },
      "ch15": {
        "steps": [
          1,
          3,
          15,
          19,
          21,
          27,
          41,
          47,
          51,
          53
        ]
      }
    },
    "Sequence7": {
      "ch0": {
        "steps": [
          1,
          15,
          19,
          21,
          27,
          31,
          33,
          47,
          51,
          53,
          59
        ]
      },
      "ch1": {
        "steps": [
          1,
          3,
          5,
          7,
          9,
          11,
          13,
          15,
          17,
          19,
          21,
          23,
          25,
          27,
          29,
          31,
          33,
          35,
          37,
          39,
          41,
          43,
          45,
          47,
          49,
          51,
          53,
          55,
          57,
          58,
          59,
          60,
          61,
          62,
          63,
          64
        ]
      },
      "ch2": {
        "steps": [
          9,
          25,
          41,
          57,
          63
        ]
      },
      "ch3": {
        "steps": []
      },
      "ch4": {
        "steps": [
          1
        ]
      },
      "ch5": {
        "steps": [
          17
        ]
      },
      "ch6": {
        "steps": [
          1,
          9,
          21,
          29
        ]
      },
      "ch7": {
        "steps": [
          3,
          7,
          23,
          27
        ]
      },
      "ch8": {
        "steps": [
          5,
          25
        ]
      },
      "ch9": {
        "steps": []
      },
      "ch10": {
        "steps": [
          1
        ]
      },
      "ch11": {
        "steps": []
      },
      "ch12": {
        "steps": [
          9,
          10,
          11,
          39,
          43
        ]
      },
      "ch13": {
        "steps": [
          15,
          19,
          33,
          49
        ]
      },
      "ch14": {
        "steps": []
      },
      "ch15": {
        "steps": [
          1,
          3,
          15,
          19,
          21,
          29,
          33,
          35,
          47,
          51,
          53
        ]
      }
    },
    "Sequence8": {
      "ch0": {
        "steps": [
          1,
          15,
          19,
          21,
          33,
          47,
          51,
          53,
          57,
          61
        ]
      },
      "ch1": {
        "steps": [
          33,
          35,
          37,
          39,
          41,
          43,
          45,
          47,
          49,
          51,
          53,
          55
        ]
      },
      "ch2": {
        "steps": [
          9,
          41,
          57,
          59,
          61
        ]
      },
      "ch3": {
        "steps": []
      },
      "ch4": {
        "steps": [
          57,
          61
        ]
      },
      "ch5": {
        "steps": []
      },
      "ch6": {
        "steps": [
          33,
          37,
          41,
          53,
          57,
          59,
          61
        ]
      },
      "ch7": {
        "steps": [
          35,
          39,
          47,
          51
        ]
      },
      "ch8": {
        "steps": [
          36,
          37,
          49,
          57,
          59,
          61
        ]
      },
      "ch9": {
        "steps": [
          1,
          15,
          19,
          21
        ]
      },
      "ch10": {
        "steps": []
      },
      "ch11": {
        "steps": []
      },
      "ch12": {
        "steps": [
          1,
          2,
          3,
          5,
          7,
          17
        ]
      },
      "ch13": {
        "steps": [
          21,
          47,
          51
        ]
      },
      "ch14": {
        "steps": [
          25,
          57
        ]
      },
      "ch15": {
        "steps": [
          9,
          11,
          33,
          35,
          47,
          51,
          53
        ]
      }
    },
    "Sequence9": {
      "ch0": {
        "steps": [
          1,
          15,
          19,
          21,
          27,
          31,
          33,
          47,
          51,
          53,
          59
        ]
      },
      "ch1": {
        "steps": [
          1,
          3,
          5,
          7,
          9,
          11,
          13,
          15,
          17,
          19,
          21,
          23,
          25,
          27,
          29,
          31,
          33,
          35,
          37,
          39,
          41,
          43,
          45,
          47,
          49,
          51,
          53,
          55,
          57,
          58,
          59,
          60,
          61,
          62,
          63,
          64
        ]
      },
      "ch2": {
        "steps": [
          9,
          25,
          41,
          57,
          63
        ]
      },
      "ch3": {
        "steps": []
      },
      "ch4": {
        "steps": [
          1
        ]
      },
      "ch5": {
        "steps": [
          37
        ]
      },
      "ch6": {
        "steps": [
          1,
          9,
          21,
          29
        ]
      },
      "ch7": {
        "steps": [
          3,
          7,
          23,
          27
        ]
      },
      "ch8": {
        "steps": [
          5,
          25
        ]
      },
      "ch9": {
        "steps": []
      },
      "ch10": {
        "steps": [
          1
        ]
      },
      "ch11": {
        "steps": []
      },
      "ch12": {
        "steps": [
          29,
          30,
          31,
          33
        ]
      },
      "ch13": {
        "steps": [
          15,
          19,
          49
        ]
      },
      "ch14": {
        "steps": [
          25,
          57
        ]
      },
      "ch15": {
        "steps": [
          1,
          3,
          15,
          19,
          21,
          35,
          47,
          51,
          53
        ]
      }
    },
    "Sequence10": {
      "ch0": {
        "steps": [
          1,
          15,
          19,
          21,
          27,
          31,
          33,
          47,
          51,
          53
        ]
      },
      "ch1": {
        "steps": [
          1,
          3,
          5,
          7,
          9,
          11,
          13,
          15,
          17,
          19,
          21,
          23,
          25,
          27,
          29,
          31,
          33,
          35,
          37,
          39,
          41,
          43,
          45,
          47,
          49,
          51,
          53,
          55
        ]
      },
      "ch2": {
        "steps": [
          9,
          25,
          41,
          57
        ]
      },
      "ch3": {
        "steps": [
          57,
          59
        ]
      },
      "ch4": {
        "steps": [
          1
        ]
      },
      "ch5": {
        "steps": []
      },
      "ch6": {
        "steps": [
          1,
          9,
          21,
          29
        ]
      },
      "ch7": {
        "steps": [
          3,
          7,
          23,
          27
        ]
      },
      "ch8": {
        "steps": [
          5,
          25
        ]
      },
      "ch9": {
        "steps": []
      },
      "ch10": {
        "steps": [
          {
            "index": 1,
            "reverse": true
          }
        ]
      },
      "ch11": {
        "steps": []
      },
      "ch12": {
        "steps": [
          29,
          30,
          31,
          33
        ]
      },
      "ch13": {
        "steps": [
          15,
          19,
          49
        ]
      },
      "ch14": {
        "steps": [
          25,
          57
        ]
      },
      "ch15": {
        "steps": [
          1,
          3,
          15,
          19,
          21,
          35,
          47,
          51,
          53
        ]
      }
    },
    "Sequence11": {
      "ch0": {
        "steps": [
          1,
          15,
          19,
          21,
          27,
          31,
          33,
          47,
          51,
          53,
          59,
          63
        ]
      },
      "ch1": {
        "steps": [
          1,
          3,
          5,
          7,
          9,
          10,
          11,
          13,
          15,
          17,
          19,
          21,
          23,
          25,
          27,
          29,
          31,
          33,
          35,
          37,
          39,
          41,
          42,
          43,
          45,
          47,
          49,
          51,
          53,
          55,
          57,
          59,
          61,
          63
        ]
      },
      "ch2": {
        "steps": [
          9,
          25,
          41,
          57
        ]
      },
      "ch3": {
        "steps": []
      },
      "ch4": {
        "steps": [
          1,
          33
        ]
      },
      "ch5": {
        "steps": [
          17
        ]
      },
      "ch6": {
        "steps": []
      },
      "ch7": {
        "steps": []
      },
      "ch8": {
        "steps": []
      },
      "ch9": {
        "steps": []
      },
      "ch10": {
        "steps": [
          1
        ]
      },
      "ch11": {
        "steps": [
          17,
          33
        ]
      },
      "ch12": {
        "steps": [
          5,
          7,
          9,
          10,
          11,
          41,
          43
        ]
      },
      "ch13": {
        "steps": [
          21,
          45,
          49
        ]
      },
      "ch14": {
        "steps": [
          25,
          55,
          59
        ]
      },
      "ch15": {
        "steps": [
          1,
          3,
          29,
          30,
          31,
          32,
          61,
          63
        ]
      }
    },
    "Sequence12": {
      "ch0": {
        "steps": [
          1,
          15,
          19,
          21,
          27,
          31,
          33,
          47,
          51,
          53,
          59,
          63
        ]
      },
      "ch1": {
        "steps": [
          1,
          3,
          5,
          7,
          9,
          10,
          11,
          13,
          15,
          17,
          19,
          21,
          23,
          25,
          27,
          29,
          31,
          33,
          35,
          37,
          39,
          41,
          42,
          43,
          45,
          47,
          49,
          51,
          53,
          55,
          57,
          59,
          61,
          63
        ]
      },
      "ch2": {
        "steps": [
          9,
          25,
          41,
          57
        ]
      },
      "ch3": {
        "steps": []
      },
      "ch4": {
        "steps": [
          1,
          33
        ]
      },
      "ch5": {
        "steps": []
      },
      "ch6": {
        "steps": []
      },
      "ch7": {
        "steps": []
      },
      "ch8": {
        "steps": []
      },
      "ch9": {
        "steps": []
      },
      "ch10": {
        "steps": [
          {
            "index": 1,
            "reverse": true
          }
        ]
      },
      "ch11": {
        "steps": [
          1,
          33
        ]
      },
      "ch12": {
        "steps": [
          5,
          7,
          41,
          42,
          43
        ]
      },
      "ch13": {
        "steps": [
          13,
          21,
          29,
          31,
          45,
          49
        ]
      },
      "ch14": {
        "steps": [
          17,
          25,
          55,
          59
        ]
      },
      "ch15": {
        "steps": [
          1,
          3,
          29,
          61,
          62,
          63
        ]
      }
    },
    "Sequence13": {
      "ch0": {
        "steps": [
          1,
          15,
          19,
          21,
          27,
          31,
          33,
          47,
          51,
          53,
          59,
          63
        ]
      },
      "ch1": {
        "steps": [
          1,
          3,
          5,
          7,
          9,
          10,
          11,
          13,
          15,
          17,
          19,
          21,
          23,
          25,
          27,
          29,
          31,
          33,
          35,
          37,
          39,
          41,
          42,
          43,
          45,
          47,
          49,
          51,
          53,
          55,
          57,
          59,
          61,
          63
        ]
      },
      "ch2": {
        "steps": [
          9,
          25,
          41,
          57
        ]
      },
      "ch3": {
        "steps": []
      },
      "ch4": {
        "steps": [
          1,
          33
        ]
      },
      "ch5": {
        "steps": [
          37
        ]
      },
      "ch6": {
        "steps": []
      },
      "ch7": {
        "steps": []
      },
      "ch8": {
        "steps": []
      },
      "ch9": {
        "steps": []
      },
      "ch10": {
        "steps": [
          1
        ]
      },
      "ch11": {
        "steps": [
          1,
          33
        ]
      },
      "ch12": {
        "steps": [
          5,
          7,
          41,
          43
        ]
      },
      "ch13": {
        "steps": [
          13,
          21,
          45,
          49
        ]
      },
      "ch14": {
        "steps": [
          17,
          25,
          55,
          59
        ]
      },
      "ch15": {
        "steps": [
          1,
          29,
          30,
          31,
          61,
          63
        ]
      }
    },
    "Sequence14": {
      "ch0": {
        "steps": [
          1,
          15,
          19,
          21,
          27,
          31,
          33,
          47
        ]
      },
      "ch1": {
        "steps": [
          1,
          3,
          5,
          7,
          9,
          10,
          11,
          13,
          15,
          17,
          19,
          21,
          23,
          25,
          27,
          29,
          31,
          33,
          35,
          37,
          39,
          41,
          42,
          43,
          45,
          47
        ]
      },
      "ch2": {
        "steps": [
          9,
          25,
          41,
          57
        ]
      },
      "ch3": {
        "steps": [
          49,
          51,
          53,
          55,
          57,
          59,
          61,
          63
        ]
      },
      "ch4": {
        "steps": [
          1,
          33
        ]
      },
      "ch5": {
        "steps": []
      },
      "ch6": {
        "steps": []
      },
      "ch7": {
        "steps": []
      },
      "ch8": {
        "steps": []
      },
      "ch9": {
        "steps": []
      },
      "ch10": {
        "steps": [
          {
            "index": 1,
            "reverse": true
          }
        ]
      },
      "ch11": {
        "steps": [
          33
        ]
      },
      "ch12": {
        "steps": [
          49
        ]
      },
      "ch13": {
        "steps": [
          53
        ]
      },
      "ch14": {
        "steps": [
          57
        ]
      },
      "ch15": {
        "steps": [
          1,
          3,
          5,
          15,
          19,
          21,
          29,
          33,
          35,
          47,
          51,
          53,
          55
        ]
      }
    },
    "Sequence15": {
      "ch0": {
        "steps": [
          1
        ]
      },
      "ch1": {
        "steps": []
      },
      "ch2": {
        "steps": [
          49,
          50,
          51,
          53,
          55,
          58,
          59,
          60,
          61,
          63
        ]
      },
      "ch3": {
        "steps": []
      },
      "ch4": {
        "steps": [
          1,
          {
            "index": 47,
            "reverse": true
          }
        ]
      },
      "ch5": {
        "steps": []
      },
      "ch6": {
        "steps": []
      },
      "ch7": {
        "steps": []
      },
      "ch8": {
        "steps": []
      },
      "ch9": {
        "steps": []
      },
      "ch10": {
        "steps": [
          1
        ]
      },
      "ch11": {
        "steps": []
      },
      "ch12": {
        "steps": []
      },
      "ch13": {
        "steps": []
      },
      "ch14": {
        "steps": []
      },
      "ch15": {
        "steps": []
      }
    },
    "Sequence16": {
      "ch0": {
        "steps": []
      },
      "ch1": {
        "steps": []
      },
      "ch2": {
        "steps": []
      },
      "ch3": {
        "steps": []
      },
      "ch4": {
        "steps": []
      },
      "ch5": {
        "steps": []
      },
      "ch6": {
        "steps": []
      },
      "ch7": {
        "steps": []
      },
      "ch8": {
        "steps": []
      },
      "ch9": {
        "steps": []
      },
      "ch10": {
        "steps": []
      },
      "ch11": {
        "steps": []
      },
      "ch12": {
        "steps": []
      },
      "ch13": {
        "steps": []
      },
      "ch14": {
        "steps": []
      },
      "ch15": {
        "steps": []
      }
    },
    "Sequence17": {
      "ch0": {
        "steps": []
      },
      "ch1": {
        "steps": []
      },
      "ch2": {
        "steps": []
      },
      "ch3": {
        "steps": []
      },
      "ch4": {
        "steps": []
      },
      "ch5": {
        "steps": []
      },
      "ch6": {
        "steps": []
      },
      "ch7": {
        "steps": []
      },
      "ch8": {
        "steps": []
      },
      "ch9": {
        "steps": []
      },
      "ch10": {
        "steps": []
      },
      "ch11": {
        "steps": []
      },
      "ch12": {
        "steps": []
      },
      "ch13": {
        "steps": []
      },
      "ch14": {
        "steps": []
      },
      "ch15": {
        "steps": []
      }
    },
    "Sequence18": {
      "ch0": {
        "steps": []
      },
      "ch1": {
        "steps": []
      },
      "ch2": {
        "steps": []
      },
      "ch3": {
        "steps": []
      },
      "ch4": {
        "steps": []
      },
      "ch5": {
        "steps": []
      },
      "ch6": {
        "steps": []
      },
      "ch7": {
        "steps": []
      },
      "ch8": {
        "steps": []
      },
      "ch9": {
        "steps": []
      },
      "ch10": {
        "steps": []
      },
      "ch11": {
        "steps": []
      },
      "ch12": {
        "steps": []
      },
      "ch13": {
        "steps": []
      },
      "ch14": {
        "steps": []
      },
      "ch15": {
        "steps": []
      }
    },
    "Sequence19": {
      "ch0": {
        "steps": []
      },
      "ch1": {
        "steps": []
      },
      "ch2": {
        "steps": []
      },
      "ch3": {
        "steps": []
      },
      "ch4": {
        "steps": []
      },
      "ch5": {
        "steps": []
      },
      "ch6": {
        "steps": []
      },
      "ch7": {
        "steps": []
      },
      "ch8": {
        "steps": []
      },
      "ch9": {
        "steps": []
      },
      "ch10": {
        "steps": []
      },
      "ch11": {
        "steps": []
      },
      "ch12": {
        "steps": []
      },
      "ch13": {
        "steps": []
      },
      "ch14": {
        "steps": []
      },
      "ch15": {
        "steps": []
      }
    },
    "Sequence20": {
      "ch0": {
        "steps": []
      },
      "ch1": {
        "steps": []
      },
      "ch2": {
        "steps": []
      },
      "ch3": {
        "steps": []
      },
      "ch4": {
        "steps": []
      },
      "ch5": {
        "steps": []
      },
      "ch6": {
        "steps": []
      },
      "ch7": {
        "steps": []
      },
      "ch8": {
        "steps": []
      },
      "ch9": {
        "steps": []
      },
      "ch10": {
        "steps": []
      },
      "ch11": {
        "steps": []
      },
      "ch12": {
        "steps": []
      },
      "ch13": {
        "steps": []
      },
      "ch14": {
        "steps": []
      },
      "ch15": {
        "steps": []
      }
    },
    "Sequence21": {
      "ch0": {
        "steps": []
      },
      "ch1": {
        "steps": []
      },
      "ch2": {
        "steps": []
      },
      "ch3": {
        "steps": []
      },
      "ch4": {
        "steps": []
      },
      "ch5": {
        "steps": []
      },
      "ch6": {
        "steps": []
      },
      "ch7": {
        "steps": []
      },
      "ch8": {
        "steps": []
      },
      "ch9": {
        "steps": []
      },
      "ch10": {
        "steps": []
      },
      "ch11": {
        "steps": []
      },
      "ch12": {
        "steps": []
      },
      "ch13": {
        "steps": []
      },
      "ch14": {
        "steps": []
      },
      "ch15": {
        "steps": []
      }
    },
    "Sequence22": {
      "ch0": {
        "steps": []
      },
      "ch1": {
        "steps": []
      },
      "ch2": {
        "steps": []
      },
      "ch3": {
        "steps": []
      },
      "ch4": {
        "steps": []
      },
      "ch5": {
        "steps": []
      },
      "ch6": {
        "steps": []
      },
      "ch7": {
        "steps": []
      },
      "ch8": {
        "steps": []
      },
      "ch9": {
        "steps": []
      },
      "ch10": {
        "steps": []
      },
      "ch11": {
        "steps": []
      },
      "ch12": {
        "steps": []
      },
      "ch13": {
        "steps": []
      },
      "ch14": {
        "steps": []
      },
      "ch15": {
        "steps": []
      }
    },
    "Sequence23": {
      "ch0": {
        "steps": []
      },
      "ch1": {
        "steps": []
      },
      "ch2": {
        "steps": []
      },
      "ch3": {
        "steps": []
      },
      "ch4": {
        "steps": []
      },
      "ch5": {
        "steps": []
      },
      "ch6": {
        "steps": []
      },
      "ch7": {
        "steps": []
      },
      "ch8": {
        "steps": []
      },
      "ch9": {
        "steps": []
      },
      "ch10": {
        "steps": []
      },
      "ch11": {
        "steps": []
      },
      "ch12": {
        "steps": []
      },
      "ch13": {
        "steps": []
      },
      "ch14": {
        "steps": []
      },
      "ch15": {
        "steps": []
      }
    },
    "Sequence24": {
      "ch0": {
        "steps": []
      },
      "ch1": {
        "steps": []
      },
      "ch2": {
        "steps": []
      },
      "ch3": {
        "steps": []
      },
      "ch4": {
        "steps": []
      },
      "ch5": {
        "steps": []
      },
      "ch6": {
        "steps": []
      },
      "ch7": {
        "steps": []
      },
      "ch8": {
        "steps": []
      },
      "ch9": {
        "steps": []
      },
      "ch10": {
        "steps": []
      },
      "ch11": {
        "steps": []
      },
      "ch12": {
        "steps": []
      },
      "ch13": {
        "steps": []
      },
      "ch14": {
        "steps": []
      },
      "ch15": {
        "steps": []
      }
    },
    "Sequence25": {
      "ch0": {
        "steps": []
      },
      "ch1": {
        "steps": []
      },
      "ch2": {
        "steps": []
      },
      "ch3": {
        "steps": []
      },
      "ch4": {
        "steps": []
      },
      "ch5": {
        "steps": []
      },
      "ch6": {
        "steps": []
      },
      "ch7": {
        "steps": []
      },
      "ch8": {
        "steps": []
      },
      "ch9": {
        "steps": []
      },
      "ch10": {
        "steps": []
      },
      "ch11": {
        "steps": []
      },
      "ch12": {
        "steps": []
      },
      "ch13": {
        "steps": []
      },
      "ch14": {
        "steps": []
      },
      "ch15": {
        "steps": []
      }
    },
    "Sequence26": {
      "ch0": {
        "steps": []
      },
      "ch1": {
        "steps": []
      },
      "ch2": {
        "steps": []
      },
      "ch3": {
        "steps": []
      },
      "ch4": {
        "steps": []
      },
      "ch5": {
        "steps": []
      },
      "ch6": {
        "steps": []
      },
      "ch7": {
        "steps": []
      },
      "ch8": {
        "steps": []
      },
      "ch9": {
        "steps": []
      },
      "ch10": {
        "steps": []
      },
      "ch11": {
        "steps": []
      },
      "ch12": {
        "steps": []
      },
      "ch13": {
        "steps": []
      },
      "ch14": {
        "steps": []
      },
      "ch15": {
        "steps": []
      }
    },
    "Sequence27": {
      "ch0": {
        "steps": []
      },
      "ch1": {
        "steps": []
      },
      "ch2": {
        "steps": []
      },
      "ch3": {
        "steps": []
      },
      "ch4": {
        "steps": []
      },
      "ch5": {
        "steps": []
      },
      "ch6": {
        "steps": []
      },
      "ch7": {
        "steps": []
      },
      "ch8": {
        "steps": []
      },
      "ch9": {
        "steps": []
      },
      "ch10": {
        "steps": []
      },
      "ch11": {
        "steps": []
      },
      "ch12": {
        "steps": []
      },
      "ch13": {
        "steps": []
      },
      "ch14": {
        "steps": []
      },
      "ch15": {
        "steps": []
      }
    },
    "Sequence28": {
      "ch0": {
        "steps": []
      },
      "ch1": {
        "steps": []
      },
      "ch2": {
        "steps": []
      },
      "ch3": {
        "steps": []
      },
      "ch4": {
        "steps": []
      },
      "ch5": {
        "steps": []
      },
      "ch6": {
        "steps": []
      },
      "ch7": {
        "steps": []
      },
      "ch8": {
        "steps": []
      },
      "ch9": {
        "steps": []
      },
      "ch10": {
        "steps": []
      },
      "ch11": {
        "steps": []
      },
      "ch12": {
        "steps": []
      },
      "ch13": {
        "steps": []
      },
      "ch14": {
        "steps": []
      },
      "ch15": {
        "steps": []
      }
    },
    "Sequence29": {
      "ch0": {
        "steps": []
      },
      "ch1": {
        "steps": []
      },
      "ch2": {
        "steps": []
      },
      "ch3": {
        "steps": []
      },
      "ch4": {
        "steps": []
      },
      "ch5": {
        "steps": []
      },
      "ch6": {
        "steps": []
      },
      "ch7": {
        "steps": []
      },
      "ch8": {
        "steps": []
      },
      "ch9": {
        "steps": []
      },
      "ch10": {
        "steps": []
      },
      "ch11": {
        "steps": []
      },
      "ch12": {
        "steps": []
      },
      "ch13": {
        "steps": []
      },
      "ch14": {
        "steps": []
      },
      "ch15": {
        "steps": []
      }
    },
    "Sequence30": {
      "ch0": {
        "steps": []
      },
      "ch1": {
        "steps": []
      },
      "ch2": {
        "steps": []
      },
      "ch3": {
        "steps": []
      },
      "ch4": {
        "steps": []
      },
      "ch5": {
        "steps": []
      },
      "ch6": {
        "steps": []
      },
      "ch7": {
        "steps": []
      },
      "ch8": {
        "steps": []
      },
      "ch9": {
        "steps": []
      },
      "ch10": {
        "steps": []
      },
      "ch11": {
        "steps": []
      },
      "ch12": {
        "steps": []
      },
      "ch13": {
        "steps": []
      },
      "ch14": {
        "steps": []
      },
      "ch15": {
        "steps": []
      }
    },
    "Sequence31": {
      "ch0": {
        "steps": []
      },
      "ch1": {
        "steps": []
      },
      "ch2": {
        "steps": []
      },
      "ch3": {
        "steps": []
      },
      "ch4": {
        "steps": []
      },
      "ch5": {
        "steps": []
      },
      "ch6": {
        "steps": []
      },
      "ch7": {
        "steps": []
      },
      "ch8": {
        "steps": []
      },
      "ch9": {
        "steps": []
      },
      "ch10": {
        "steps": []
      },
      "ch11": {
        "steps": []
      },
      "ch12": {
        "steps": []
      },
      "ch13": {
        "steps": []
      },
      "ch14": {
        "steps": []
      },
      "ch15": {
        "steps": []
      }
    },
    "Sequence32": {
      "ch0": {
        "steps": []
      },
      "ch1": {
        "steps": []
      },
      "ch2": {
        "steps": []
      },
      "ch3": {
        "steps": []
      },
      "ch4": {
        "steps": []
      },
      "ch5": {
        "steps": []
      },
      "ch6": {
        "steps": []
      },
      "ch7": {
        "steps": []
      },
      "ch8": {
        "steps": []
      },
      "ch9": {
        "steps": []
      },
      "ch10": {
        "steps": []
      },
      "ch11": {
        "steps": []
      },
      "ch12": {
        "steps": []
      },
      "ch13": {
        "steps": []
      },
      "ch14": {
        "steps": []
      },
      "ch15": {
        "steps": []
      }
    },
    "Sequence33": {
      "ch0": {
        "steps": []
      },
      "ch1": {
        "steps": []
      },
      "ch2": {
        "steps": []
      },
      "ch3": {
        "steps": []
      },
      "ch4": {
        "steps": []
      },
      "ch5": {
        "steps": []
      },
      "ch6": {
        "steps": []
      },
      "ch7": {
        "steps": []
      },
      "ch8": {
        "steps": []
      },
      "ch9": {
        "steps": []
      },
      "ch10": {
        "steps": []
      },
      "ch11": {
        "steps": []
      },
      "ch12": {
        "steps": []
      },
      "ch13": {
        "steps": []
      },
      "ch14": {
        "steps": []
      },
      "ch15": {
        "steps": []
      }
    },
    "Sequence34": {
      "ch0": {
        "steps": []
      },
      "ch1": {
        "steps": []
      },
      "ch2": {
        "steps": []
      },
      "ch3": {
        "steps": []
      },
      "ch4": {
        "steps": []
      },
      "ch5": {
        "steps": []
      },
      "ch6": {
        "steps": []
      },
      "ch7": {
        "steps": []
      },
      "ch8": {
        "steps": []
      },
      "ch9": {
        "steps": []
      },
      "ch10": {
        "steps": []
      },
      "ch11": {
        "steps": []
      },
      "ch12": {
        "steps": []
      },
      "ch13": {
        "steps": []
      },
      "ch14": {
        "steps": []
      },
      "ch15": {
        "steps": []
      }
    },
    "Sequence35": {
      "ch0": {
        "steps": []
      },
      "ch1": {
        "steps": []
      },
      "ch2": {
        "steps": []
      },
      "ch3": {
        "steps": []
      },
      "ch4": {
        "steps": []
      },
      "ch5": {
        "steps": []
      },
      "ch6": {
        "steps": []
      },
      "ch7": {
        "steps": []
      },
      "ch8": {
        "steps": []
      },
      "ch9": {
        "steps": []
      },
      "ch10": {
        "steps": []
      },
      "ch11": {
        "steps": []
      },
      "ch12": {
        "steps": []
      },
      "ch13": {
        "steps": []
      },
      "ch14": {
        "steps": []
      },
      "ch15": {
        "steps": []
      }
    },
    "Sequence36": {
      "ch0": {
        "steps": []
      },
      "ch1": {
        "steps": []
      },
      "ch2": {
        "steps": []
      },
      "ch3": {
        "steps": []
      },
      "ch4": {
        "steps": []
      },
      "ch5": {
        "steps": []
      },
      "ch6": {
        "steps": []
      },
      "ch7": {
        "steps": []
      },
      "ch8": {
        "steps": []
      },
      "ch9": {
        "steps": []
      },
      "ch10": {
        "steps": []
      },
      "ch11": {
        "steps": []
      },
      "ch12": {
        "steps": []
      },
      "ch13": {
        "steps": []
      },
      "ch14": {
        "steps": []
      },
      "ch15": {
        "steps": []
      }
    },
    "Sequence37": {
      "ch0": {
        "steps": []
      },
      "ch1": {
        "steps": []
      },
      "ch2": {
        "steps": []
      },
      "ch3": {
        "steps": []
      },
      "ch4": {
        "steps": []
      },
      "ch5": {
        "steps": []
      },
      "ch6": {
        "steps": []
      },
      "ch7": {
        "steps": []
      },
      "ch8": {
        "steps": []
      },
      "ch9": {
        "steps": []
      },
      "ch10": {
        "steps": []
      },
      "ch11": {
        "steps": []
      },
      "ch12": {
        "steps": []
      },
      "ch13": {
        "steps": []
      },
      "ch14": {
        "steps": []
      },
      "ch15": {
        "steps": []
      }
    },
    "Sequence38": {
      "ch0": {
        "steps": []
      },
      "ch1": {
        "steps": []
      },
      "ch2": {
        "steps": []
      },
      "ch3": {
        "steps": []
      },
      "ch4": {
        "steps": []
      },
      "ch5": {
        "steps": []
      },
      "ch6": {
        "steps": []
      },
      "ch7": {
        "steps": []
      },
      "ch8": {
        "steps": []
      },
      "ch9": {
        "steps": []
      },
      "ch10": {
        "steps": []
      },
      "ch11": {
        "steps": []
      },
      "ch12": {
        "steps": []
      },
      "ch13": {
        "steps": []
      },
      "ch14": {
        "steps": []
      },
      "ch15": {
        "steps": []
      }
    },
    "Sequence39": {
      "ch0": {
        "steps": []
      },
      "ch1": {
        "steps": []
      },
      "ch2": {
        "steps": []
      },
      "ch3": {
        "steps": []
      },
      "ch4": {
        "steps": []
      },
      "ch5": {
        "steps": []
      },
      "ch6": {
        "steps": []
      },
      "ch7": {
        "steps": []
      },
      "ch8": {
        "steps": []
      },
      "ch9": {
        "steps": []
      },
      "ch10": {
        "steps": []
      },
      "ch11": {
        "steps": []
      },
      "ch12": {
        "steps": []
      },
      "ch13": {
        "steps": []
      },
      "ch14": {
        "steps": []
      },
      "ch15": {
        "steps": []
      }
    },
    "Sequence40": {
      "ch0": {
        "steps": []
      },
      "ch1": {
        "steps": []
      },
      "ch2": {
        "steps": []
      },
      "ch3": {
        "steps": []
      },
      "ch4": {
        "steps": []
      },
      "ch5": {
        "steps": []
      },
      "ch6": {
        "steps": []
      },
      "ch7": {
        "steps": []
      },
      "ch8": {
        "steps": []
      },
      "ch9": {
        "steps": []
      },
      "ch10": {
        "steps": []
      },
      "ch11": {
        "steps": []
      },
      "ch12": {
        "steps": []
      },
      "ch13": {
        "steps": []
      },
      "ch14": {
        "steps": []
      },
      "ch15": {
        "steps": []
      }
    },
    "Sequence41": {
      "ch0": {
        "steps": []
      },
      "ch1": {
        "steps": []
      },
      "ch2": {
        "steps": []
      },
      "ch3": {
        "steps": []
      },
      "ch4": {
        "steps": []
      },
      "ch5": {
        "steps": []
      },
      "ch6": {
        "steps": []
      },
      "ch7": {
        "steps": []
      },
      "ch8": {
        "steps": []
      },
      "ch9": {
        "steps": []
      },
      "ch10": {
        "steps": []
      },
      "ch11": {
        "steps": []
      },
      "ch12": {
        "steps": []
      },
      "ch13": {
        "steps": []
      },
      "ch14": {
        "steps": []
      },
      "ch15": {
        "steps": []
      }
    },
    "Sequence42": {
      "ch0": {
        "steps": []
      },
      "ch1": {
        "steps": []
      },
      "ch2": {
        "steps": []
      },
      "ch3": {
        "steps": []
      },
      "ch4": {
        "steps": []
      },
      "ch5": {
        "steps": []
      },
      "ch6": {
        "steps": []
      },
      "ch7": {
        "steps": []
      },
      "ch8": {
        "steps": []
      },
      "ch9": {
        "steps": []
      },
      "ch10": {
        "steps": []
      },
      "ch11": {
        "steps": []
      },
      "ch12": {
        "steps": []
      },
      "ch13": {
        "steps": []
      },
      "ch14": {
        "steps": []
      },
      "ch15": {
        "steps": []
      }
    },
    "Sequence43": {
      "ch0": {
        "steps": []
      },
      "ch1": {
        "steps": []
      },
      "ch2": {
        "steps": []
      },
      "ch3": {
        "steps": []
      },
      "ch4": {
        "steps": []
      },
      "ch5": {
        "steps": []
      },
      "ch6": {
        "steps": []
      },
      "ch7": {
        "steps": []
      },
      "ch8": {
        "steps": []
      },
      "ch9": {
        "steps": []
      },
      "ch10": {
        "steps": []
      },
      "ch11": {
        "steps": []
      },
      "ch12": {
        "steps": []
      },
      "ch13": {
        "steps": []
      },
      "ch14": {
        "steps": []
      },
      "ch15": {
        "steps": []
      }
    },
    "Sequence44": {
      "ch0": {
        "steps": []
      },
      "ch1": {
        "steps": []
      },
      "ch2": {
        "steps": []
      },
      "ch3": {
        "steps": []
      },
      "ch4": {
        "steps": []
      },
      "ch5": {
        "steps": []
      },
      "ch6": {
        "steps": []
      },
      "ch7": {
        "steps": []
      },
      "ch8": {
        "steps": []
      },
      "ch9": {
        "steps": []
      },
      "ch10": {
        "steps": []
      },
      "ch11": {
        "steps": []
      },
      "ch12": {
        "steps": []
      },
      "ch13": {
        "steps": []
      },
      "ch14": {
        "steps": []
      },
      "ch15": {
        "steps": []
      }
    },
    "Sequence45": {
      "ch0": {
        "steps": []
      },
      "ch1": {
        "steps": []
      },
      "ch2": {
        "steps": []
      },
      "ch3": {
        "steps": []
      },
      "ch4": {
        "steps": []
      },
      "ch5": {
        "steps": []
      },
      "ch6": {
        "steps": []
      },
      "ch7": {
        "steps": []
      },
      "ch8": {
        "steps": []
      },
      "ch9": {
        "steps": []
      },
      "ch10": {
        "steps": []
      },
      "ch11": {
        "steps": []
      },
      "ch12": {
        "steps": []
      },
      "ch13": {
        "steps": []
      },
      "ch14": {
        "steps": []
      },
      "ch15": {
        "steps": []
      }
    },
    "Sequence46": {
      "ch0": {
        "steps": []
      },
      "ch1": {
        "steps": []
      },
      "ch2": {
        "steps": []
      },
      "ch3": {
        "steps": []
      },
      "ch4": {
        "steps": []
      },
      "ch5": {
        "steps": []
      },
      "ch6": {
        "steps": []
      },
      "ch7": {
        "steps": []
      },
      "ch8": {
        "steps": []
      },
      "ch9": {
        "steps": []
      },
      "ch10": {
        "steps": []
      },
      "ch11": {
        "steps": []
      },
      "ch12": {
        "steps": []
      },
      "ch13": {
        "steps": []
      },
      "ch14": {
        "steps": []
      },
      "ch15": {
        "steps": []
      }
    },
    "Sequence47": {
      "ch0": {
        "steps": []
      },
      "ch1": {
        "steps": []
      },
      "ch2": {
        "steps": []
      },
      "ch3": {
        "steps": []
      },
      "ch4": {
        "steps": []
      },
      "ch5": {
        "steps": []
      },
      "ch6": {
        "steps": []
      },
      "ch7": {
        "steps": []
      },
      "ch8": {
        "steps": []
      },
      "ch9": {
        "steps": []
      },
      "ch10": {
        "steps": []
      },
      "ch11": {
        "steps": []
      },
      "ch12": {
        "steps": []
      },
      "ch13": {
        "steps": []
      },
      "ch14": {
        "steps": []
      },
      "ch15": {
        "steps": []
      }
    },
    "Sequence48": {
      "ch0": {
        "steps": []
      },
      "ch1": {
        "steps": []
      },
      "ch2": {
        "steps": []
      },
      "ch3": {
        "steps": []
      },
      "ch4": {
        "steps": []
      },
      "ch5": {
        "steps": []
      },
      "ch6": {
        "steps": []
      },
      "ch7": {
        "steps": []
      },
      "ch8": {
        "steps": []
      },
      "ch9": {
        "steps": []
      },
      "ch10": {
        "steps": []
      },
      "ch11": {
        "steps": []
      },
      "ch12": {
        "steps": []
      },
      "ch13": {
        "steps": []
      },
      "ch14": {
        "steps": []
      },
      "ch15": {
        "steps": []
      }
    },
    "Sequence49": {
      "ch0": {
        "steps": []
      },
      "ch1": {
        "steps": []
      },
      "ch2": {
        "steps": []
      },
      "ch3": {
        "steps": []
      },
      "ch4": {
        "steps": []
      },
      "ch5": {
        "steps": []
      },
      "ch6": {
        "steps": []
      },
      "ch7": {
        "steps": []
      },
      "ch8": {
        "steps": []
      },
      "ch9": {
        "steps": []
      },
      "ch10": {
        "steps": []
      },
      "ch11": {
        "steps": []
      },
      "ch12": {
        "steps": []
      },
      "ch13": {
        "steps": []
      },
      "ch14": {
        "steps": []
      },
      "ch15": {
        "steps": []
      }
    },
    "Sequence50": {
      "ch0": {
        "steps": []
      },
      "ch1": {
        "steps": []
      },
      "ch2": {
        "steps": []
      },
      "ch3": {
        "steps": []
      },
      "ch4": {
        "steps": []
      },
      "ch5": {
        "steps": []
      },
      "ch6": {
        "steps": []
      },
      "ch7": {
        "steps": []
      },
      "ch8": {
        "steps": []
      },
      "ch9": {
        "steps": []
      },
      "ch10": {
        "steps": []
      },
      "ch11": {
        "steps": []
      },
      "ch12": {
        "steps": []
      },
      "ch13": {
        "steps": []
      },
      "ch14": {
        "steps": []
      },
      "ch15": {
        "steps": []
      }
    },
    "Sequence51": {
      "ch0": {
        "steps": []
      },
      "ch1": {
        "steps": []
      },
      "ch2": {
        "steps": []
      },
      "ch3": {
        "steps": []
      },
      "ch4": {
        "steps": []
      },
      "ch5": {
        "steps": []
      },
      "ch6": {
        "steps": []
      },
      "ch7": {
        "steps": []
      },
      "ch8": {
        "steps": []
      },
      "ch9": {
        "steps": []
      },
      "ch10": {
        "steps": []
      },
      "ch11": {
        "steps": []
      },
      "ch12": {
        "steps": []
      },
      "ch13": {
        "steps": []
      },
      "ch14": {
        "steps": []
      },
      "ch15": {
        "steps": []
      }
    },
    "Sequence52": {
      "ch0": {
        "steps": []
      },
      "ch1": {
        "steps": []
      },
      "ch2": {
        "steps": []
      },
      "ch3": {
        "steps": []
      },
      "ch4": {
        "steps": []
      },
      "ch5": {
        "steps": []
      },
      "ch6": {
        "steps": []
      },
      "ch7": {
        "steps": []
      },
      "ch8": {
        "steps": []
      },
      "ch9": {
        "steps": []
      },
      "ch10": {
        "steps": []
      },
      "ch11": {
        "steps": []
      },
      "ch12": {
        "steps": []
      },
      "ch13": {
        "steps": []
      },
      "ch14": {
        "steps": []
      },
      "ch15": {
        "steps": []
      }
    },
    "Sequence53": {
      "ch0": {
        "steps": []
      },
      "ch1": {
        "steps": []
      },
      "ch2": {
        "steps": []
      },
      "ch3": {
        "steps": []
      },
      "ch4": {
        "steps": []
      },
      "ch5": {
        "steps": []
      },
      "ch6": {
        "steps": []
      },
      "ch7": {
        "steps": []
      },
      "ch8": {
        "steps": []
      },
      "ch9": {
        "steps": []
      },
      "ch10": {
        "steps": []
      },
      "ch11": {
        "steps": []
      },
      "ch12": {
        "steps": []
      },
      "ch13": {
        "steps": []
      },
      "ch14": {
        "steps": []
      },
      "ch15": {
        "steps": []
      }
    },
    "Sequence54": {
      "ch0": {
        "steps": []
      },
      "ch1": {
        "steps": []
      },
      "ch2": {
        "steps": []
      },
      "ch3": {
        "steps": []
      },
      "ch4": {
        "steps": []
      },
      "ch5": {
        "steps": []
      },
      "ch6": {
        "steps": []
      },
      "ch7": {
        "steps": []
      },
      "ch8": {
        "steps": []
      },
      "ch9": {
        "steps": []
      },
      "ch10": {
        "steps": []
      },
      "ch11": {
        "steps": []
      },
      "ch12": {
        "steps": []
      },
      "ch13": {
        "steps": []
      },
      "ch14": {
        "steps": []
      },
      "ch15": {
        "steps": []
      }
    },
    "Sequence55": {
      "ch0": {
        "steps": []
      },
      "ch1": {
        "steps": []
      },
      "ch2": {
        "steps": []
      },
      "ch3": {
        "steps": []
      },
      "ch4": {
        "steps": []
      },
      "ch5": {
        "steps": []
      },
      "ch6": {
        "steps": []
      },
      "ch7": {
        "steps": []
      },
      "ch8": {
        "steps": []
      },
      "ch9": {
        "steps": []
      },
      "ch10": {
        "steps": []
      },
      "ch11": {
        "steps": []
      },
      "ch12": {
        "steps": []
      },
      "ch13": {
        "steps": []
      },
      "ch14": {
        "steps": []
      },
      "ch15": {
        "steps": []
      }
    },
    "Sequence56": {
      "ch0": {
        "steps": []
      },
      "ch1": {
        "steps": []
      },
      "ch2": {
        "steps": []
      },
      "ch3": {
        "steps": []
      },
      "ch4": {
        "steps": []
      },
      "ch5": {
        "steps": []
      },
      "ch6": {
        "steps": []
      },
      "ch7": {
        "steps": []
      },
      "ch8": {
        "steps": []
      },
      "ch9": {
        "steps": []
      },
      "ch10": {
        "steps": []
      },
      "ch11": {
        "steps": []
      },
      "ch12": {
        "steps": []
      },
      "ch13": {
        "steps": []
      },
      "ch14": {
        "steps": []
      },
      "ch15": {
        "steps": []
      }
    },
    "Sequence57": {
      "ch0": {
        "steps": []
      },
      "ch1": {
        "steps": []
      },
      "ch2": {
        "steps": []
      },
      "ch3": {
        "steps": []
      },
      "ch4": {
        "steps": []
      },
      "ch5": {
        "steps": []
      },
      "ch6": {
        "steps": []
      },
      "ch7": {
        "steps": []
      },
      "ch8": {
        "steps": []
      },
      "ch9": {
        "steps": []
      },
      "ch10": {
        "steps": []
      },
      "ch11": {
        "steps": []
      },
      "ch12": {
        "steps": []
      },
      "ch13": {
        "steps": []
      },
      "ch14": {
        "steps": []
      },
      "ch15": {
        "steps": []
      }
    },
    "Sequence58": {
      "ch0": {
        "steps": []
      },
      "ch1": {
        "steps": []
      },
      "ch2": {
        "steps": []
      },
      "ch3": {
        "steps": []
      },
      "ch4": {
        "steps": []
      },
      "ch5": {
        "steps": []
      },
      "ch6": {
        "steps": []
      },
      "ch7": {
        "steps": []
      },
      "ch8": {
        "steps": []
      },
      "ch9": {
        "steps": []
      },
      "ch10": {
        "steps": []
      },
      "ch11": {
        "steps": []
      },
      "ch12": {
        "steps": []
      },
      "ch13": {
        "steps": []
      },
      "ch14": {
        "steps": []
      },
      "ch15": {
        "steps": []
      }
    },
    "Sequence59": {
      "ch0": {
        "steps": []
      },
      "ch1": {
        "steps": []
      },
      "ch2": {
        "steps": []
      },
      "ch3": {
        "steps": []
      },
      "ch4": {
        "steps": []
      },
      "ch5": {
        "steps": []
      },
      "ch6": {
        "steps": []
      },
      "ch7": {
        "steps": []
      },
      "ch8": {
        "steps": []
      },
      "ch9": {
        "steps": []
      },
      "ch10": {
        "steps": []
      },
      "ch11": {
        "steps": []
      },
      "ch12": {
        "steps": []
      },
      "ch13": {
        "steps": []
      },
      "ch14": {
        "steps": []
      },
      "ch15": {
        "steps": []
      }
    },
    "Sequence60": {
      "ch0": {
        "steps": []
      },
      "ch1": {
        "steps": []
      },
      "ch2": {
        "steps": []
      },
      "ch3": {
        "steps": []
      },
      "ch4": {
        "steps": []
      },
      "ch5": {
        "steps": []
      },
      "ch6": {
        "steps": []
      },
      "ch7": {
        "steps": []
      },
      "ch8": {
        "steps": []
      },
      "ch9": {
        "steps": []
      },
      "ch10": {
        "steps": []
      },
      "ch11": {
        "steps": []
      },
      "ch12": {
        "steps": []
      },
      "ch13": {
        "steps": []
      },
      "ch14": {
        "steps": []
      },
      "ch15": {
        "steps": []
      }
    },
    "Sequence61": {
      "ch0": {
        "steps": []
      },
      "ch1": {
        "steps": []
      },
      "ch2": {
        "steps": []
      },
      "ch3": {
        "steps": []
      },
      "ch4": {
        "steps": []
      },
      "ch5": {
        "steps": []
      },
      "ch6": {
        "steps": []
      },
      "ch7": {
        "steps": []
      },
      "ch8": {
        "steps": []
      },
      "ch9": {
        "steps": []
      },
      "ch10": {
        "steps": []
      },
      "ch11": {
        "steps": []
      },
      "ch12": {
        "steps": []
      },
      "ch13": {
        "steps": []
      },
      "ch14": {
        "steps": []
      },
      "ch15": {
        "steps": []
      }
    },
    "Sequence62": {
      "ch0": {
        "steps": []
      },
      "ch1": {
        "steps": []
      },
      "ch2": {
        "steps": []
      },
      "ch3": {
        "steps": []
      },
      "ch4": {
        "steps": []
      },
      "ch5": {
        "steps": []
      },
      "ch6": {
        "steps": []
      },
      "ch7": {
        "steps": []
      },
      "ch8": {
        "steps": []
      },
      "ch9": {
        "steps": []
      },
      "ch10": {
        "steps": []
      },
      "ch11": {
        "steps": []
      },
      "ch12": {
        "steps": []
      },
      "ch13": {
        "steps": []
      },
      "ch14": {
        "steps": []
      },
      "ch15": {
        "steps": []
      }
    },
    "Sequence63": {
      "ch0": {
        "steps": []
      },
      "ch1": {
        "steps": []
      },
      "ch2": {
        "steps": []
      },
      "ch3": {
        "steps": []
      },
      "ch4": {
        "steps": []
      },
      "ch5": {
        "steps": []
      },
      "ch6": {
        "steps": []
      },
      "ch7": {
        "steps": []
      },
      "ch8": {
        "steps": []
      },
      "ch9": {
        "steps": []
      },
      "ch10": {
        "steps": []
      },
      "ch11": {
        "steps": []
      },
      "ch12": {
        "steps": []
      },
      "ch13": {
        "steps": []
      },
      "ch14": {
        "steps": []
      },
      "ch15": {
        "steps": []
      }
    }
  },
  "globalPlaybackSpeed": 1
}