{
    "projectName": "8-Bit Bounce",
    "bpm": 135,
    "channels": [
      {
        "name": "8 Bit Loop Layer 1",
        "steps": [
          true, false, false, false, false, false, false, false, true, false, false, false, false, false, false, false,
          true, false, false, false, false, false, false, false, true, false, false, false, false, false, false, false,
          true, false, false, false, false, false, false, false, true, false, false, false, false, false, false, false,
          true, false, false, false, false, false, false, true, true, false, false, false, false, false, false, false
        ],
        "src": "3364803cb3032ce95f4138a214c15a9b36dcb70f574a477f27615d448e1cdeb8i0",
        "volume": 0.7, "mute": false, "solo": false, "pitch": 0, "reverse": false, "trimStart": 0, "trimEnd": 1,
        "hpfCutoff": 20, "hpfQ": 0.707, "lpfCutoff": 20000, "lpfQ": 0.707, "eqLowGain": 0, "eqMidGain": 0, "eqHighGain": 0,
        "fadeInTime": 0, "fadeOutTime": 0, "activePlaybackScheduledTime": null, "activePlaybackDuration": null,
        "activePlaybackTrimStart": 0, "activePlaybackTrimEnd": 1, "activePlaybackReversed": null
      },
      {
        "name": "8 Bit Loop Layer 2",
        "steps": [
          false, false, false, false, true, false, false, false, false, false, false, false, true, false, false, false,
          false, false, false, false, true, false, false, false, false, false, false, false, true, false, false, false,
          false, false, false, false, true, false, false, false, false, false, false, false, true, false, false, false,
          false, false, false, true, true, false, false, false, false, false, false, false, true, false, false, true
        ],
        "src": "3364803cb3032ce95f4138a214c15a9b36dcb70f574a477f27615d448e1cdeb8i0",
        "volume": 0.6, "mute": false, "solo": false, "pitch": 2, "reverse": false, "trimStart": 0.1, "trimEnd": 0.9,
        "hpfCutoff": 100, "hpfQ": 0.707, "lpfCutoff": 15000, "lpfQ": 0.707, "eqLowGain": 0, "eqMidGain": 0, "eqHighGain": 0,
        "fadeInTime": 0, "fadeOutTime": 0, "activePlaybackScheduledTime": null, "activePlaybackDuration": null,
        "activePlaybackTrimStart": 0.1, "activePlaybackTrimEnd": 0.9, "activePlaybackReversed": null
      },
      {
        "name": "Glocken Melody",
        "steps": [
          true, false, false, true, false, true, false, false, true, false, false, false, true, false, false, false,
          true, false, false, true, false, true, false, true, true, false, false, true, false, false, false, false,
          true, false, false, true, false, true, false, false, true, false, false, false, true, false, false, true,
          true, false, false, true, false, true, false, false, true, false, true, false, false, true, false, false
        ],
        "src": "578aa9d3b29ceceafc659ecee22cb7ef1a063ba5b71474db8fe84949746cdeefi0",
        "volume": 0.65, "mute": false, "solo": false, "pitch": 0, "reverse": false, "trimStart": 0, "trimEnd": 0.3,
        "hpfCutoff": 500, "hpfQ": 0.707, "lpfCutoff": 12000, "lpfQ": 0.707, "eqLowGain": 0, "eqMidGain": 0, "eqHighGain": 0,
        "fadeInTime": 0, "fadeOutTime": 0.01, "activePlaybackScheduledTime": null, "activePlaybackDuration": null,
        "activePlaybackTrimStart": 0, "activePlaybackTrimEnd": 0.3, "activePlaybackReversed": null
      },
      {
        "name": "Small Click Perc",
        "steps": [
          false, true, false, true, false, true, false, true, false, true, false, true, false, true, false, true,
          false, true, false, true, false, true, false, true, false, true, false, true, false, true, false, true,
          false, true, false, true, false, true, false, true, false, true, false, true, false, true, false, true,
          false, true, false, true, false, true, true, true, false, true, false, true, true, true, false, true
        ],
        "src": "1bda678460ef08fb64435b57c9b69fd78fd4556822ccd8e9839b4eb71b3621edi0",
        "volume": 0.5, "mute": false, "solo": false, "pitch": 5, "reverse": false, "trimStart": 0, "trimEnd": 0.1,
        "hpfCutoff": 1000, "hpfQ": 0.707, "lpfCutoff": 20000, "lpfQ": 0.707, "eqLowGain": 0, "eqMidGain": 0, "eqHighGain": 0,
        "fadeInTime": 0, "fadeOutTime": 0, "activePlaybackScheduledTime": null, "activePlaybackDuration": null,
        "activePlaybackTrimStart": 0, "activePlaybackTrimEnd": 0.1, "activePlaybackReversed": null
      },
      {
        "name": "Synth Bass 3 Punch",
        "steps": [
          true, false, false, false, false, false, true, false, false, false, true, false, false, false, false, false,
          true, false, false, false, false, false, true, false, true, false, true, false, false, false, false, false,
          true, false, false, false, false, false, true, false, false, false, true, false, false, true, false, false,
          true, false, false, false, true, false, true, false, true, false, false, false, true, false, false, false
        ],
        "src": "1e3c2571e96729153e4b63e2b561d85aec7bc5ba372d293af469a525dfa3ed59i0",
        "volume": 0.8, "mute": false, "solo": false, "pitch": 0, "reverse": false, "trimStart": 0, "trimEnd": 0.2,
        "hpfCutoff": 40, "hpfQ": 0.707, "lpfCutoff": 1000, "lpfQ": 0.9, "eqLowGain": 1, "eqMidGain": 0, "eqHighGain": 0,
        "fadeInTime": 0, "fadeOutTime": 0.02, "activePlaybackScheduledTime": null, "activePlaybackDuration": null,
        "activePlaybackTrimStart": 0, "activePlaybackTrimEnd": 0.2, "activePlaybackReversed": null
      },
      {
        "name": "Bitcoin Mel H",
        "steps": [
          false, false, false, false, false, false, false, false, true, false, false, false, false, false, false, false,
          false, false, false, false, false, false, false, false, false, false, false, false, false, false, false, false,
          false, false, false, false, true, false, false, false, false, false, false, false, false, false, false, false,
          false, false, false, false, false, false, false, false, false, false, false, false, false, false, false, false
        ],
        "src": "4f9bed6449d99ef3cbb0fabefac6890c20ef17db2bfe7c07f1386cb43277f220i0",
        "volume": 0.6, "mute": false, "solo": false, "pitch": 0, "reverse": true, "trimStart": 0, "trimEnd": 1,
        "hpfCutoff": 200, "hpfQ": 0.707, "lpfCutoff": 10000, "lpfQ": 0.707, "eqLowGain": 0, "eqMidGain": 0, "eqHighGain": 0,
        "fadeInTime": 0.05, "fadeOutTime": 0.1, "activePlaybackScheduledTime": null, "activePlaybackDuration": null,
        "activePlaybackTrimStart": 0, "activePlaybackTrimEnd": 1, "activePlaybackReversed": null
      },
      {
        "name": "Crash Riser",
        "steps": [
          false, false, false, false, false, false, false, false, false, false, false, false, false, false, false, false,
          false, false, false, false, false, false, false, false, false, false, false, false, false, false, false, true,
          false, false, false, false, false, false, false, false, false, false, false, false, false, false, false, false,
          false, false, false, false, false, false, false, false, false, false, false, false, false, false, false, true
        ],
        "src": "5a42d7b2e2fe01e4f31cbad5dd671997f87339d970faaab37f6355c4a2f3be5ai0",
        "volume": 0.7, "mute": false, "solo": false, "pitch": 5, "reverse": true, "trimStart": 0.1, "trimEnd": 0.8,
        "hpfCutoff": 100, "hpfQ": 0.707, "lpfCutoff": 20000, "lpfQ": 0.707, "eqLowGain": 0, "eqMidGain": 0, "eqHighGain": 0,
        "fadeInTime": 0, "fadeOutTime": 0, "activePlaybackScheduledTime": null, "activePlaybackDuration": null,
        "activePlaybackTrimStart": 0.1, "activePlaybackTrimEnd": 0.8, "activePlaybackReversed": null
      },
      {
        "name": "Denim Tom Bounce",
        "steps": [
          false,false,false,false,true,false,false,false,false,false,false,false,false,false,true,false,
          false,false,false,false,true,false,false,false,false,false,false,true,false,false,false,false,
          false,false,false,false,true,false,false,false,false,false,false,false,false,false,true,false,
          false,false,true,false,true,false,false,false,false,false,false,false,true,false,false,false
        ],
        "src": "a511d79317efac68fea3b14070bebe208aefde07ce1c55d6f4cfe42e8273cbdbi0",
        "volume": 0.6, "mute": false, "solo": false, "pitch": 3, "reverse": false, "trimStart": 0, "trimEnd": 0.4,
        "hpfCutoff": 100, "hpfQ": 0.707, "lpfCutoff": 12000, "lpfQ": 0.707, "eqLowGain": 0, "eqMidGain": 0, "eqHighGain": 0,
        "fadeInTime": 0, "fadeOutTime": 0.01, "activePlaybackScheduledTime": null, "activePlaybackDuration": null,
        "activePlaybackTrimStart": 0, "activePlaybackTrimEnd": 0.4, "activePlaybackReversed": null
      },
      { "name": "Channel 9", "steps": [false,false,false,false,false,false,false,false,false,false,false,false,false,false,false,false,false,false,false,false,false,false,false,false,false,false,false,false,false,false,false,false,false,false,false,false,false,false,false,false,false,false,false,false,false,false,false,false,false,false,false,false,false,false,false,false,false,false,false,false,false,false,false,false], "src": null, "volume": 0.8, "mute": false, "solo": false, "pitch": 0, "reverse": false, "trimStart": 0, "trimEnd": 1, "hpfCutoff": 20, "hpfQ": 0.707, "lpfCutoff": 20000, "lpfQ": 0.707, "eqLowGain": 0, "eqMidGain": 0, "eqHighGain": 0, "fadeInTime": 0, "fadeOutTime": 0, "activePlaybackScheduledTime": null, "activePlaybackDuration": null, "activePlaybackTrimStart": null, "activePlaybackTrimEnd": null, "activePlaybackReversed": null },
      { "name": "Channel 10", "steps": [false,false,false,false,false,false,false,false,false,false,false,false,false,false,false,false,false,false,false,false,false,false,false,false,false,false,false,false,false,false,false,false,false,false,false,false,false,false,false,false,false,false,false,false,false,false,false,false,false,false,false,false,false,false,false,false,false,false,false,false,false,false,false,false], "src": null, "volume": 0.8, "mute": false, "solo": false, "pitch": 0, "reverse": false, "trimStart": 0, "trimEnd": 1, "hpfCutoff": 20, "hpfQ": 0.707, "lpfCutoff": 20000, "lpfQ": 0.707, "eqLowGain": 0, "eqMidGain": 0, "eqHighGain": 0, "fadeInTime": 0, "fadeOutTime": 0, "activePlaybackScheduledTime": null, "activePlaybackDuration": null, "activePlaybackTrimStart": null, "activePlaybackTrimEnd": null, "activePlaybackReversed": null },
      { "name": "Channel 11", "steps": [false,false,false,false,false,false,false,false,false,false,false,false,false,false,false,false,false,false,false,false,false,false,false,false,false,false,false,false,false,false,false,false,false,false,false,false,false,false,false,false,false,false,false,false,false,false,false,false,false,false,false,false,false,false,false,false,false,false,false,false,false,false,false,false], "src": null, "volume": 0.8, "mute": false, "solo": false, "pitch": 0, "reverse": false, "trimStart": 0, "trimEnd": 1, "hpfCutoff": 20, "hpfQ": 0.707, "lpfCutoff": 20000, "lpfQ": 0.707, "eqLowGain": 0, "eqMidGain": 0, "eqHighGain": 0, "fadeInTime": 0, "fadeOutTime": 0, "activePlaybackScheduledTime": null, "activePlaybackDuration": null, "activePlaybackTrimStart": null, "activePlaybackTrimEnd": null, "activePlaybackReversed": null },
      { "name": "Channel 12", "steps": [false,false,false,false,false,false,false,false,false,false,false,false,false,false,false,false,false,false,false,false,false,false,false,false,false,false,false,false,false,false,false,false,false,false,false,false,false,false,false,false,false,false,false,false,false,false,false,false,false,false,false,false,false,false,false,false,false,false,false,false,false,false,false,false], "src": null, "volume": 0.8, "mute": false, "solo": false, "pitch": 0, "reverse": false, "trimStart": 0, "trimEnd": 1, "hpfCutoff": 20, "hpfQ": 0.707, "lpfCutoff": 20000, "lpfQ": 0.707, "eqLowGain": 0, "eqMidGain": 0, "eqHighGain": 0, "fadeInTime": 0, "fadeOutTime": 0, "activePlaybackScheduledTime": null, "activePlaybackDuration": null, "activePlaybackTrimStart": null, "activePlaybackTrimEnd": null, "activePlaybackReversed": null },
      { "name": "Channel 13", "steps": [false,false,false,false,false,false,false,false,false,false,false,false,false,false,false,false,false,false,false,false,false,false,false,false,false,false,false,false,false,false,false,false,false,false,false,false,false,false,false,false,false,false,false,false,false,false,false,false,false,false,false,false,false,false,false,false,false,false,false,false,false,false,false,false], "src": null, "volume": 0.8, "mute": false, "solo": false, "pitch": 0, "reverse": false, "trimStart": 0, "trimEnd": 1, "hpfCutoff": 20, "hpfQ": 0.707, "lpfCutoff": 20000, "lpfQ": 0.707, "eqLowGain": 0, "eqMidGain": 0, "eqHighGain": 0, "fadeInTime": 0, "fadeOutTime": 0, "activePlaybackScheduledTime": null, "activePlaybackDuration": null, "activePlaybackTrimStart": null, "activePlaybackTrimEnd": null, "activePlaybackReversed": null },
      { "name": "Channel 14", "steps": [false,false,false,false,false,false,false,false,false,false,false,false,false,false,false,false,false,false,false,false,false,false,false,false,false,false,false,false,false,false,false,false,false,false,false,false,false,false,false,false,false,false,false,false,false,false,false,false,false,false,false,false,false,false,false,false,false,false,false,false,false,false,false,false], "src": null, "volume": 0.8, "mute": false, "solo": false, "pitch": 0, "reverse": false, "trimStart": 0, "trimEnd": 1, "hpfCutoff": 20, "hpfQ": 0.707, "lpfCutoff": 20000, "lpfQ": 0.707, "eqLowGain": 0, "eqMidGain": 0, "eqHighGain": 0, "fadeInTime": 0, "fadeOutTime": 0, "activePlaybackScheduledTime": null, "activePlaybackDuration": null, "activePlaybackTrimStart": null, "activePlaybackTrimEnd": null, "activePlaybackReversed": null },
      { "name": "Channel 15", "steps": [false,false,false,false,false,false,false,false,false,false,false,false,false,false,false,false,false,false,false,false,false,false,false,false,false,false,false,false,false,false,false,false,false,false,false,false,false,false,false,false,false,false,false,false,false,false,false,false,false,false,false,false,false,false,false,false,false,false,false,false,false,false,false,false], "src": null, "volume": 0.8, "mute": false, "solo": false, "pitch": 0, "reverse": false, "trimStart": 0, "trimEnd": 1, "hpfCutoff": 20, "hpfQ": 0.707, "lpfCutoff": 20000, "lpfQ": 0.707, "eqLowGain": 0, "eqMidGain": 0, "eqHighGain": 0, "fadeInTime": 0, "fadeOutTime": 0, "activePlaybackScheduledTime": null, "activePlaybackDuration": null, "activePlaybackTrimStart": null, "activePlaybackTrimEnd": null, "activePlaybackReversed": null },
      { "name": "Channel 16", "steps": [false,false,false,false,false,false,false,false,false,false,false,false,false,false,false,false,false,false,false,false,false,false,false,false,false,false,false,false,false,false,false,false,false,false,false,false,false,false,false,false,false,false,false,false,false,false,false,false,false,false,false,false,false,false,false,false,false,false,false,false,false,false,false,false], "src": null, "volume": 0.8, "mute": false, "solo": false, "pitch": 0, "reverse": false, "trimStart": 0, "trimEnd": 1, "hpfCutoff": 20, "hpfQ": 0.707, "lpfCutoff": 20000, "lpfQ": 0.707, "eqLowGain": 0, "eqMidGain": 0, "eqHighGain": 0, "fadeInTime": 0, "fadeOutTime": 0, "activePlaybackScheduledTime": null, "activePlaybackDuration": null, "activePlaybackTrimStart": null, "activePlaybackTrimEnd": null, "activePlaybackReversed": null }
    ],
    "playing": false,
    "currentStep": 0
  }